{
  "provider": "espn",
  "competition": "serie-b",
  "season": "2025-26",
  "stage": "playout",
  "retrievedAt": "2026-07-18T17:39:27.477Z",
  "matches": [
    {
      "id": "serie-b-2025-26-401872118",
      "provider": "espn",
      "providerFixtureId": "401872118",
      "competition": "serie-b",
      "competitionName": "Serie B",
      "season": "2025-26",
      "stage": "playout",
      "matchday": null,
      "date": "2026-05-15T18:00Z",
      "homeTeam": {
        "id": "106",
        "name": "Bari",
        "slug": "bari",
        "providerName": "Bari"
      },
      "awayTeam": {
        "id": "11139",
        "name": "Südtirol",
        "slug": "sudtirol",
        "providerName": "Sudtirol"
      },
      "score": {
        "home": 0,
        "away": 0
      },
      "status": "STATUS_FULL_TIME",
      "referee": {
        "name": "Antonio Rapuano",
        "slug": "antonio-rapuano",
        "providerName": "Antonio Rapuano",
        "providerId": null
      },
      "teamStats": {
        "home": {
          "teamId": "106",
          "teamName": "Bari",
          "fouls": 17,
          "yellowCards": 4,
          "secondYellowCards": 0,
          "straightRedCards": 0,
          "penaltiesFor": 0,
          "penaltiesAgainst": 0,
          "teamSlug": "bari"
        },
        "away": {
          "teamId": "11139",
          "teamName": "Südtirol",
          "fouls": 17,
          "yellowCards": 2,
          "secondYellowCards": 0,
          "straightRedCards": 0,
          "penaltiesFor": 0,
          "penaltiesAgainst": 0,
          "teamSlug": "sudtirol"
        }
      },
      "source": {
        "provider": "espn",
        "fixtureId": "401872118",
        "url": "https://www.espn.com/soccer/match/_/gameId/401872118",
        "summaryUrl": "https://site.api.espn.com/apis/site/v2/sports/soccer/ita.2/summary?event=401872118",
        "retrievedAt": "2026-07-18T17:39:27.477Z"
      },
      "missingFields": []
    },
    {
      "id": "serie-b-2025-26-401872123",
      "provider": "espn",
      "providerFixtureId": "401872123",
      "competition": "serie-b",
      "competitionName": "Serie B",
      "season": "2025-26",
      "stage": "playout",
      "matchday": null,
      "date": "2026-05-22T18:00Z",
      "homeTeam": {
        "id": "11139",
        "name": "Südtirol",
        "slug": "sudtirol",
        "providerName": "Sudtirol"
      },
      "awayTeam": {
        "id": "106",
        "name": "Bari",
        "slug": "bari",
        "providerName": "Bari"
      },
      "score": {
        "home": 0,
        "away": 0
      },
      "status": "STATUS_FULL_TIME",
      "referee": {
        "name": "Federico La Penna",
        "slug": "federico-la-penna",
        "providerName": "Federico La Penna",
        "providerId": null
      },
      "teamStats": {
        "home": {
          "teamId": "11139",
          "teamName": "Südtirol",
          "fouls": 20,
          "yellowCards": 1,
          "secondYellowCards": 0,
          "straightRedCards": 0,
          "penaltiesFor": 0,
          "penaltiesAgainst": 0,
          "teamSlug": "sudtirol"
        },
        "away": {
          "teamId": "106",
          "teamName": "Bari",
          "fouls": 23,
          "yellowCards": 3,
          "secondYellowCards": 0,
          "straightRedCards": 1,
          "penaltiesFor": 0,
          "penaltiesAgainst": 0,
          "teamSlug": "bari"
        }
      },
      "source": {
        "provider": "espn",
        "fixtureId": "401872123",
        "url": "https://www.espn.com/soccer/match/_/gameId/401872123",
        "summaryUrl": "https://site.api.espn.com/apis/site/v2/sports/soccer/ita.2/summary?event=401872123",
        "retrievedAt": "2026-07-18T17:39:27.477Z"
      },
      "missingFields": []
    }
  ]
}
